.travis.yml
NOTICE.txt
README.rst
bootstrap.py
buildout.cfg
edrnsite.portlets.sublime-project
setup.cfg
setup.py
travis.cfg
docs/HISTORY.txt
docs/INSTALL.txt
docs/LICENSE.txt
edrnsite/__init__.py
edrnsite.portlets.egg-info/PKG-INFO
edrnsite.portlets.egg-info/SOURCES.txt
edrnsite.portlets.egg-info/dependency_links.txt
edrnsite.portlets.egg-info/entry_points.txt
edrnsite.portlets.egg-info/namespace_packages.txt
edrnsite.portlets.egg-info/not-zip-safe
edrnsite.portlets.egg-info/requires.txt
edrnsite.portlets.egg-info/top_level.txt
edrnsite/portlets/__init__.py
edrnsite/portlets/configure.zcml
edrnsite/portlets/testing.py
edrnsite/portlets/upgrades.py
edrnsite/portlets/upgrades.zcml
edrnsite/portlets/portlets/__init__.py
edrnsite/portlets/portlets/configure.zcml
edrnsite/portlets/portlets/dmccrss.pt
edrnsite/portlets/portlets/dmccrss.py
edrnsite/portlets/portlets/quicklinks.pt
edrnsite/portlets/portlets/quicklinks.py
edrnsite/portlets/profiles/default/metadata.xml
edrnsite/portlets/profiles/default/portlets.xml
edrnsite/portlets/tests/__init__.py
edrnsite/portlets/tests/testDMCCRSS.py
edrnsite/portlets/tests/testQuickLinks.py
parts/omelette/edrnsite/portlets/__init__.py
parts/omelette/edrnsite/portlets/configure.zcml
parts/omelette/edrnsite/portlets/testing.py
parts/omelette/edrnsite/portlets/upgrades.py
parts/omelette/edrnsite/portlets/upgrades.zcml
parts/omelette/edrnsite/portlets/portlets/__init__.py
parts/omelette/edrnsite/portlets/portlets/configure.zcml
parts/omelette/edrnsite/portlets/portlets/dmccrss.pt
parts/omelette/edrnsite/portlets/portlets/dmccrss.py
parts/omelette/edrnsite/portlets/portlets/quicklinks.pt
parts/omelette/edrnsite/portlets/portlets/quicklinks.py
parts/omelette/edrnsite/portlets/profiles/default/metadata.xml
parts/omelette/edrnsite/portlets/profiles/default/portlets.xml
parts/omelette/edrnsite/portlets/tests/__init__.py
parts/omelette/edrnsite/portlets/tests/testDMCCRSS.py
parts/omelette/edrnsite/portlets/tests/testQuickLinks.py