Metadata-Version: 1.1
Name: edrnsite.portlets
Version: 1.1.8
Summary: Portlets for the EDRN Public Portal
Home-page: https://github.com/EDRN/edrnsite.portlets
Author: Sean Kelly
Author-email: sean.kelly@jpl.nasa.gov
License: ALv2
Keywords: web zope plone edrn cancer biomarkers portlet
Platform: UNKNOWN
Classifier: Development Status :: 4 - Beta
Classifier: Environment :: Web Environment
Classifier: Framework :: Plone
Classifier: Intended Audience :: Healthcare Industry
Classifier: Intended Audience :: Science/Research
Classifier: License :: OSI Approved :: Apache Software License
Classifier: Operating System :: OS Independent
Classifier: Programming Language :: Python
Classifier: Topic :: Internet :: WWW/HTTP
Classifier: Topic :: Scientific/Engineering :: Bio-Informatics
Classifier: Topic :: Software Development :: Libraries :: Python Modules
